MANIFEST.in
README.md
setup.py
memristivenetworks/BMI.data.csv
memristivenetworks/__init__.py
memristivenetworks/__init__.pyc
memristivenetworks/breast-cancer-wisconsin.data.csv
memristivenetworks/breast-cancer-wisconsin.data_all.csv
memristivenetworks/perceptron.py
memristivenetworks/perceptron.pyc
memristivenetworks/reset.csv
memristivenetworks/set.csv
memristivenetworks/sonar.all-data.csv
memristivenetworks/willshaw.py
memristivenetworks/willshaw.pyc
memristivenetworks.egg-info/PKG-INFO
memristivenetworks.egg-info/SOURCES.txt
memristivenetworks.egg-info/dependency_links.txt
memristivenetworks.egg-info/not-zip-safe
memristivenetworks.egg-info/requires.txt
memristivenetworks.egg-info/top_level.txt