Metadata-Version: 1.1
Name: memristivenetworks
Version: 0.0.1
Summary: Library for simulating memristive networks
Home-page: https://github.com/danieljosesilva/memristivenetworks
Author: Daniel Silva
Author-email: djsilva99@gmail.com
License: MIT
Platform: UNKNOWN
Classifier: Development Status :: 3 - Alpha
Classifier: License :: OSI Approved :: MIT License
Classifier: Programming Language :: Python :: 2.7
Classifier: Topic :: Scientific/Engineering :: Physics
